alegria/__init__.py
alegria/alegria.py
alegria/cli.py
alegria-0.1.0.dist-info/AUTHORS.rst
alegria-0.1.0.dist-info/LICENSE
alegria-0.1.0.dist-info/METADATA
alegria-0.1.0.dist-info/WHEEL
alegria-0.1.0.dist-info/entry_points.txt
alegria-0.1.0.dist-info/top_level.txt
alegria-0.1.0.dist-info/RECORD
